<?xml version="1.0" encoding="UTF-8"?>
<info>
  <body>
    <div xml:id="ppr-lectio92">
      <head xml:id="ppr-l92-Hldcldc">Lectio 92, de Caritate</head>
      <div xml:id="ppr-l92-Dd1e109">
        <head xml:id="ppr-l92-Haaraar">Ad aliam rationem</head>
        <p xml:id="ppr-l92-aarsdi">
          <assertions>
            <assertion property="isRelatedTo" target="http://scta.info/resource/l92-aarsdi"/>
          </assertions>
        </p>
        <p xml:id="ppr-l92-pqainb">
          <assertions>
            <assertion property="isRelatedTo" target="http://scta.info/resource/l92-pqainb"/>
          </assertions>
        </p>
        <p xml:id="ppr-l92-ssqnmp">
          <assertions>
            <assertion property="isRelatedTo" target="http://scta.info/resource/l92-ssqnmp"/>
          </assertions>
        </p>
        <p xml:id="ppr-l92-rpqhpg">
          <assertions>
            <assertion property="isRelatedTo" target="http://scta.info/resource/l92-rpqhpg"/>
          </assertions>
        </p>
        <p xml:id="ppr-l92-sqcada">
          <assertions>
            <assertion property="isRelatedTo" target="http://scta.info/resource/l92-sqcada"/>
          </assertions>
        </p>
        <div xml:id="ppr-l92-Dd1e133">
          <head xml:id="ppr-l92-Hobitio">Obiectio</head>
          <p xml:id="ppr-l92-scaisc">
            <assertions>
              <assertion property="isRelatedTo" target="http://scta.info/resource/l92-scaisc"/>
            </assertions>
          </p>
        </div>
        <div xml:id="ppr-l92-Dd1e142">
          <head xml:id="ppr-l92-Hraorao">Responsio ad obiectionem</head>
          <p xml:id="ppr-l92-rqcdpn">
            <assertions>
              <assertion property="isRelatedTo" target="http://scta.info/resource/l92-rqcdpn"/>
            </assertions>
          </p>
          <p xml:id="ppr-l92-esqcid">
            <assertions>
              <assertion property="isRelatedTo" target="http://scta.info/resource/l92-esqcid"/>
            </assertions>
          </p>
          <p xml:id="ppr-l92-snsppv">
            <assertions>
              <assertion property="isRelatedTo" target="http://scta.info/resource/l92-snsppv"/>
            </assertions>
          </p>
        </div>
        <div xml:id="ppr-l92-Dd1e157">
          <head xml:id="ppr-l92-Hddpapm">De differentia peccati venialis a peccato mortali</head>
          <p xml:id="ppr-l92-neaevp">
            <assertions>
              <assertion property="isRelatedTo" target="http://scta.info/resource/l92-neaevp"/>
            </assertions>
          </p>
          <p xml:id="ppr-l92-sdgnia">
            <assertions>
              <assertion property="isRelatedTo" target="http://scta.info/resource/l92-sdgnia"/>
            </assertions>
          </p>
          <p xml:id="ppr-l92-aapamd">
            <assertions>
              <assertion property="isRelatedTo" target="http://scta.info/resource/l92-aapamd"/>
            </assertions>
          </p>
          <p xml:id="ppr-l92-cqrecl">
            <assertions>
              <assertion property="isRelatedTo" target="http://scta.info/resource/l92-cqrecl"/>
            </assertions>
          </p>
          <p xml:id="ppr-l92-eipvem">
            <assertions>
              <assertion property="isRelatedTo" target="http://scta.info/resource/l92-eipvem"/>
            </assertions>
          </p>
          <!-- unnecessary break here -->
          <p xml:id="ppr-l92-neqepi">
            <assertions>
              <assertion property="isRelatedTo" target="http://scta.info/resource/l92-neqepi"/>
            </assertions>
          </p>
          <p xml:id="ppr-l92-siifqd">
            <assertions>
              <assertion property="isRelatedTo" target="http://scta.info/resource/l92-siifqd"/>
            </assertions>
          </p>
          <p xml:id="ppr-l92-sephfd">
            <assertions>
              <assertion property="isRelatedTo" target="http://scta.info/resource/l92-sephfd"/>
            </assertions>
          </p>
          <!-- fuzzy break -->
          <p xml:id="ppr-l92-somami">
            <assertions>
              <assertion property="isRelatedTo" target="http://scta.info/resource/l92-somami"/>
            </assertions>
          </p>
        </div>
        <div xml:id="ppr-l92-Dd1e198">
          <head xml:id="ppr-l92-Huvpprg">Utrum veniale peccatum remittat gratiam?</head>
          <p xml:id="ppr-l92-vtaedo">
            <assertions>
              <assertion property="isRelatedTo" target="http://scta.info/resource/l92-vtaedo"/>
            </assertions>
          </p>
          <p xml:id="ppr-l92-qdqdga">
            <assertions>
              <assertion property="isRelatedTo" target="http://scta.info/resource/l92-qdqdga"/>
            </assertions>
          </p>
          <p xml:id="ppr-l92-adcqaa">
            <assertions>
              <assertion property="isRelatedTo" target="http://scta.info/resource/l92-adcqaa"/>
            </assertions>
          </p>
          <!-- break is "ordinato" seems a little off here -->
          <p xml:id="ppr-l92-ttpugg">
            <assertions>
              <assertion property="isRelatedTo" target="http://scta.info/resource/l92-ttpugg"/>
            </assertions>
          </p>
          <!-- fuzzy break -->
          <p xml:id="ppr-l92-etgmgr">
            <assertions>
              <assertion property="isRelatedTo" target="http://scta.info/resource/l92-etgmgr"/>
            </assertions>
          </p>
          <p xml:id="ppr-l92-sqnmgg">
            <assertions>
              <assertion property="isRelatedTo" target="http://scta.info/resource/l92-sqnmgg"/>
            </assertions>
          </p>
          <p xml:id="ppr-l92-upieep">
            <assertions>
              <assertion property="isRelatedTo" target="http://scta.info/resource/l92-upieep"/>
            </assertions>
          </p>
        </div>
        <div xml:id="ppr-l92-Dd1e244">
          <head xml:id="ppr-l92-Hraocpv">Responsio ad obiectionem circa peccatum venialem</head>
          <p xml:id="ppr-l92-etrrpv">
            <assertions>
              <assertion property="isRelatedTo" target="http://scta.info/resource/l92-etrrpv"/>
            </assertions>
          </p>
          <!-- fuzzy break -->
          <p xml:id="ppr-l92-rqnipm">
            <assertions>
              <assertion property="isRelatedTo" target="http://scta.info/resource/l92-rqnipm"/>
            </assertions>
          </p>
          <p xml:id="ppr-l92-adipip">
            <assertions>
              <assertion property="isRelatedTo" target="http://scta.info/resource/l92-adipip"/>
            </assertions>
          </p>
          <p xml:id="ppr-l92-eehepm">
            <assertions>
              <assertion property="isRelatedTo" target="http://scta.info/resource/l92-eehepm"/>
            </assertions>
          </p>
          <p xml:id="ppr-l92-espsep">
            <assertions>
              <assertion property="isRelatedTo" target="http://scta.info/resource/l92-espsep"/>
            </assertions>
          </p>
        </div>
      </div>
      <div xml:id="ppr-l92-Dd1e278">
        <head xml:id="ppr-l92-Haaqnei">Ad argumentum quod caritas non est intensiblis</head>
        <p xml:id="ppr-l92-daqesl">
          <assertions>
            <assertion property="isRelatedTo" target="http://scta.info/resource/l92-daqesl"/>
          </assertions>
        </p>
        <p xml:id="ppr-l92-irqidp">
          <assertions>
            <assertion property="isRelatedTo" target="http://scta.info/resource/l92-irqidp"/>
          </assertions>
        </p>
        <p xml:id="ppr-l92-cthtap">
          <assertions>
            <assertion property="isRelatedTo" target="http://scta.info/resource/l92-cthtap"/>
          </assertions>
        </p>
      </div>
    </div>
  </body>
</info>